tussh/__init__.py
tussh/app.py
tussh/cli.py
tussh/config_io.py
tussh/modals.py
tussh/settings.py
tussh/styles.tcss
tussh/widgets.py
tussh-0.5.0.dist-info/METADATA
tussh-0.5.0.dist-info/WHEEL
tussh-0.5.0.dist-info/entry_points.txt
tussh-0.5.0.dist-info/RECORD
