Metadata-Version: 2.1
Name: tussh
Version: 0.5.0
Summary: A fast, responsive Textual TUI for managing and launching SSH hosts from your OpenSSH config.
License: MIT
Author: Kim Schulz
Author-email: kim@schulz.dk
Requires-Python: >=3.10,<4.0.0
Classifier: License :: OSI Approved :: MIT License
Classifier: Programming Language :: Python :: 3
Classifier: Programming Language :: Python :: 3.10
Classifier: Programming Language :: Python :: 3.11
Classifier: Programming Language :: Python :: 3.12
Requires-Dist: platformdirs (>=4.0.0)
Requires-Dist: textual (>=0.58.0)
